sleepyseagull_upgrader/__init__.py
sleepyseagull_upgrader/upgrader.py
sleepyseagull_upgrader-0.2.0.dist-info/METADATA
sleepyseagull_upgrader-0.2.0.dist-info/WHEEL
sleepyseagull_upgrader-0.2.0.dist-info/RECORD
