Metadata-Version: 2.1
Name: sleepyseagull-upgrader
Version: 0.2.0
Summary: My first published python project
Author: My name
Author-email: me@myhome.edu
Requires-Python: >=3.11,<4.0
Classifier: Programming Language :: Python :: 3
Classifier: Programming Language :: Python :: 3.11
